[{"properties": {"Name": "Kolton Johnson", "LinkedIn": "https://www.linkedin.com/in/kolton-johnson-0a4851183/", "Function": "Heavy Equipment Mechanic", "Location": "[\"Idaho\"]", "Company": "[\"https://app.notion.com/p/17b90644d524805588ecf7f399f27e9d\"]"}, "icon": "🔬", "content": "## Role\n- Heavy Equipment Mechanic at Kiewit. ([LinkedIn](https://www.linkedin.com/in/kolton-johnson-0a4851183/) · Apollo CSV export)"}, {"properties": {"Name": "JEFFREY POLLOCK", "LinkedIn": "https://www.linkedin.com/in/jeffrey-pollock-26b738187/", "Function": "Project Engineer", "Location": "[\"Texas\"]", "Company": "[\"https://app.notion.com/p/17b90644d524805588ecf7f399f27e9d\"]"}, "icon": "👷", "content": "## Role\n- Project Engineer at Kiewit. ([LinkedIn](https://www.linkedin.com/in/jeffrey-pollock-26b738187/) · Apollo CSV export)"}, {"properties": {"Name": "Brian Hilbers", "LinkedIn": "https://www.linkedin.com/in/brian-hilbers-a35a9912/", "Function": "Structural Designer", "Location": "[\"Missouri\"]", "Company": "[\"https://app.notion.com/p/17b90644d524805588ecf7f399f27e9d\"]"}, "icon": "🏗️", "content": "## Role\n- Structural Designer at Kiewit. ([LinkedIn](https://www.linkedin.com/in/brian-hilbers-a35a9912/) · Apollo CSV export)"}, {"properties": {"Name": "Tyler Davis", "LinkedIn": "https://www.linkedin.com/in/tyler-davis-a44ba788/", "Function": "General Superintendent", "Location": "[\"Washington\"]", "Company": "[\"https://app.notion.com/p/17b90644d524805588ecf7f399f27e9d\"]"}, "icon": "🧱", "content": "## Role\n- General Superintendent at Kiewit. ([LinkedIn](https://www.linkedin.com/in/tyler-davis-a44ba788/) · Apollo CSV export)"}, {"properties": {"Name": "Carlos Loomis", "LinkedIn": "https://www.linkedin.com/in/carlos-loomis-650106195/", "Function": "Construction Laborer", "Location": "[\"California\"]", "Company": "[\"https://app.notion.com/p/17b90644d524805588ecf7f399f27e9d\"]"}, "icon": "📐", "content": "## Role\n- Construction Laborer at Kiewit. ([LinkedIn](https://www.linkedin.com/in/carlos-loomis-650106195/) · Apollo CSV export)"}, {"properties": {"Name": "Eric DeHerrera", "LinkedIn": "https://www.linkedin.com/in/eric-deherrera-98a482320/", "Function": "Foreman", "Location": "[\"Colorado\"]", "Company": "[\"https://app.notion.com/p/17b90644d524805588ecf7f399f27e9d\"]"}, "icon": "⚙️", "content": "## Role\n- Foreman at Kiewit. ([LinkedIn](https://www.linkedin.com/in/eric-deherrera-98a482320/) · Apollo CSV export)"}, {"properties": {"Name": "Glen Tonack", "LinkedIn": "https://www.linkedin.com/in/glen-tonack-692909168/", "Function": "QC Manager", "Location": "[\"New York\"]", "Company": "[\"https://app.notion.com/p/17b90644d524805588ecf7f399f27e9d\"]"}, "icon": "🔧", "content": "## Role\n- QC Manager at Kiewit. ([LinkedIn](https://www.linkedin.com/in/glen-tonack-692909168/) · Apollo CSV export)"}, {"properties": {"Name": "Coralee Wolter", "LinkedIn": "https://www.linkedin.com/in/coralee-wolter-243a5213/", "Function": "Exec. Sec'y", "Location": "[\"Arizona\"]", "Company": "[\"https://app.notion.com/p/17b90644d524805588ecf7f399f27e9d\"]"}, "icon": "🔩", "content": "## Role\n- Exec. Sec'y at Kiewit. ([LinkedIn](https://www.linkedin.com/in/coralee-wolter-243a5213/) · Apollo CSV export)"}, {"properties": {"Name": "Kyle Dabney", "LinkedIn": "https://www.linkedin.com/in/kyle-dabney-079726a6/", "Function": "Safety supervisor", "Location": "[\"USA\"]", "Company": "[\"https://app.notion.com/p/17b90644d524805588ecf7f399f27e9d\"]"}, "icon": "🏢", "content": "## Role\n- Safety supervisor at Kiewit. ([LinkedIn](https://www.linkedin.com/in/kyle-dabney-079726a6/) · Apollo CSV export)"}, {"properties": {"Name": "Clifford Gaspar", "LinkedIn": "https://www.linkedin.com/in/clifford-gaspar-207b12106/", "Function": "Registered Nurse", "Location": "[\"USA\"]", "Company": "[\"https://app.notion.com/p/17b90644d524805588ecf7f399f27e9d\"]"}, "icon": "📋", "content": "## Role\n- Registered Nurse at Kiewit. ([LinkedIn](https://www.linkedin.com/in/clifford-gaspar-207b12106/) · Apollo CSV export)"}, {"properties": {"Name": "Robert MacKenzie", "LinkedIn": "https://www.linkedin.com/in/robert-mackenzie-0b95b45/", "Function": "Engineer", "Location": "[\"Washington\"]", "Company": "[\"https://app.notion.com/p/17b90644d524805588ecf7f399f27e9d\"]"}, "icon": "🗂️", "content": "## Role\n- Engineer at Kiewit Pacific. ([LinkedIn](https://www.linkedin.com/in/robert-mackenzie-0b95b45/) · Apollo CSV export)"}, {"properties": {"Name": "Abel Reyna", "LinkedIn": "https://www.linkedin.com/in/abel-reyna-83910315a/", "Function": "Welder", "Location": "[\"Kansas\"]", "Company": "[\"https://app.notion.com/p/17b90644d524805588ecf7f399f27e9d\"]"}, "icon": "📊", "content": "## Role\n- Welder at Kiewit. ([LinkedIn](https://www.linkedin.com/in/abel-reyna-83910315a/) · Apollo CSV export)"}, {"properties": {"Name": "Anna Kuriakose", "LinkedIn": "https://www.linkedin.com/in/anna-kuriakose-569109261/", "Function": "Senior Project Controls Analyst", "Location": "[\"Texas\"]", "Company": "[\"https://app.notion.com/p/17b90644d524805588ecf7f399f27e9d\"]"}, "icon": "🔨", "content": "## Role\n- Senior Project Controls Analyst at Kiewit. ([LinkedIn](https://www.linkedin.com/in/anna-kuriakose-569109261/) · Apollo CSV export)"}, {"properties": {"Name": "Joseph Jones", "LinkedIn": "https://www.linkedin.com/in/joseph-jones-1ab32318/", "Function": "Field Engineer", "Location": "[\"Maryland\"]", "Company": "[\"https://app.notion.com/p/17b90644d524805588ecf7f399f27e9d\"]"}, "icon": "⛏️", "content": "## Role\n- Field Engineer at Kiewit. ([LinkedIn](https://www.linkedin.com/in/joseph-jones-1ab32318/) · Apollo CSV export)"}, {"properties": {"Name": "Justin Hunt", "LinkedIn": "https://www.linkedin.com/in/justin-hunt-22239a10a/", "Function": "Senior Electrical Designer Substation Designer", "Location": "[\"Kansas\"]", "Company": "[\"https://app.notion.com/p/17b90644d524805588ecf7f399f27e9d\"]"}, "icon": "🚧", "content": "## Role\n- Senior Electrical Designer Substation Designer at Kiewit. ([LinkedIn](https://www.linkedin.com/in/justin-hunt-22239a10a/) · Apollo CSV export)"}, {"properties": {"Name": "Joe Miedreich", "LinkedIn": "https://www.linkedin.com/in/joe-miedreich-50036541/", "Function": "Superintendent", "Location": "[\"New York\"]", "Company": "[\"https://app.notion.com/p/17b90644d524805588ecf7f399f27e9d\"]"}, "icon": "🏛️", "content": "## Role\n- Superintendent at Kiewit. ([LinkedIn](https://www.linkedin.com/in/joe-miedreich-50036541/) · Apollo CSV export)"}, {"properties": {"Name": "Shelby Henry", "LinkedIn": "https://www.linkedin.com/in/shelby-henry-80a231232/", "Function": "SJW2", "Location": "[\"Tennessee\"]", "Company": "[\"https://app.notion.com/p/17b90644d524805588ecf7f399f27e9d\"]"}, "icon": "🏭", "content": "## Role\n- SJW2 at Kiewit. ([LinkedIn](https://www.linkedin.com/in/shelby-henry-80a231232/) · Apollo CSV export)"}, {"properties": {"Name": "Ronnie Ronnie.Edmonds", "LinkedIn": "https://www.linkedin.com/in/ronnie-ronnie-edmonds-1105567b/", "Function": "Discipline Superintendent", "Location": "[\"Georgia\"]", "Company": "[\"https://app.notion.com/p/17b90644d524805588ecf7f399f27e9d\"]"}, "icon": "📏", "content": "## Role\n- Discipline Superintendent at Kiewit. ([LinkedIn](https://www.linkedin.com/in/ronnie-ronnie-edmonds-1105567b/) · Apollo CSV export)"}, {"properties": {"Name": "Kenneth Oathout", "LinkedIn": "https://www.linkedin.com/in/kenneth-oathout-a969a016/", "Function": "Senior Mechanical Designer", "Location": "[\"Kansas\"]", "Company": "[\"https://app.notion.com/p/17b90644d524805588ecf7f399f27e9d\"]"}, "icon": "🔬", "content": "## Role\n- Senior Mechanical Designer at Kiewit Power Engineers Co.. ([LinkedIn](https://www.linkedin.com/in/kenneth-oathout-a969a016/) · Apollo CSV export)"}, {"properties": {"Name": "Volney LeBaron", "LinkedIn": "https://www.linkedin.com/in/volney-lebaron-b0011a5b/", "Function": "Field Coordinator /Logistics Engineer", "Location": "[\"Louisiana\"]", "Company": "[\"https://app.notion.com/p/17b90644d524805588ecf7f399f27e9d\"]"}, "icon": "👷", "content": "## Role\n- Field Coordinator /Logistics Engineer at Kiewit. ([LinkedIn](https://www.linkedin.com/in/volney-lebaron-b0011a5b/) · Apollo CSV export)"}, {"properties": {"Name": "David Coughlin", "LinkedIn": "https://www.linkedin.com/in/david-coughlin-a311b0187/", "Function": "Journeyman", "Location": "[\"California\"]", "Company": "[\"https://app.notion.com/p/17b90644d524805588ecf7f399f27e9d\"]"}, "icon": "🏗️", "content": "## Role\n- Journeyman at Kiewit. ([LinkedIn](https://www.linkedin.com/in/david-coughlin-a311b0187/) · Apollo CSV export)"}, {"properties": {"Name": "Juan A Anderson", "LinkedIn": "https://www.linkedin.com/in/juan-a-anderson-29621b90/", "Function": "Superintendent", "Location": "[\"Miami\"]", "Company": "[\"https://app.notion.com/p/17b90644d524805588ecf7f399f27e9d\"]"}, "icon": "🧱", "content": "## Role\n- Superintendent at Kiewit. ([LinkedIn](https://www.linkedin.com/in/juan-a-anderson-29621b90/) · Apollo CSV export)"}, {"properties": {"Name": "Ivory Hill", "LinkedIn": "https://www.linkedin.com/in/ivory-hill-b19b225/", "Function": "Document Control Specialist", "Location": "[\"Idaho\"]", "Company": "[\"https://app.notion.com/p/17b90644d524805588ecf7f399f27e9d\"]"}, "icon": "📐", "content": "## Role\n- Document Control Specialist at Kiewit. ([LinkedIn](https://www.linkedin.com/in/ivory-hill-b19b225/) · Apollo CSV export)"}, {"properties": {"Name": "Mike Belsky", "LinkedIn": "https://www.linkedin.com/in/mike-belsky-10b34851/", "Function": "Structural Steel Superintendent", "Location": "[\"New Jersey\"]", "Company": "[\"https://app.notion.com/p/17b90644d524805588ecf7f399f27e9d\"]"}, "icon": "⚙️", "content": "## Role\n- Structural Steel Superintendent at Kiewit. ([LinkedIn](https://www.linkedin.com/in/mike-belsky-10b34851/) · Apollo CSV export)"}, {"properties": {"Name": "Randy Schroeger", "LinkedIn": "https://www.linkedin.com/in/randy-schroeger-50456b57/", "Function": "Electrical & Controls Designer", "Location": "[\"Kansas\"]", "Company": "[\"https://app.notion.com/p/17b90644d524805588ecf7f399f27e9d\"]"}, "icon": "🔧", "content": "## Role\n- Electrical & Controls Designer at Kiewit. ([LinkedIn](https://www.linkedin.com/in/randy-schroeger-50456b57/) · Apollo CSV export)"}, {"properties": {"Name": "Jim Weiding", "LinkedIn": "https://www.linkedin.com/in/jim-weiding-5981921aa/", "Function": "Surveyor", "Location": "[\"Washington\"]", "Company": "[\"https://app.notion.com/p/17b90644d524805588ecf7f399f27e9d\"]"}, "icon": "🔩", "content": "## Role\n- Surveyor at Kiewit. ([LinkedIn](https://www.linkedin.com/in/jim-weiding-5981921aa/) · Apollo CSV export)"}, {"properties": {"Name": "Jacob Albers", "LinkedIn": "https://www.linkedin.com/in/jacob-albers-82372115/", "Function": "Business Line Manager - Wind", "Location": "[\"USA\"]", "Company": "[\"https://app.notion.com/p/17b90644d524805588ecf7f399f27e9d\"]"}, "icon": "🏢", "content": "## Role\n- Business Line Manager - Wind at Kiewit. ([LinkedIn](https://www.linkedin.com/in/jacob-albers-82372115/) · Apollo CSV export)"}, {"properties": {"Name": "Anita Forbes", "LinkedIn": "https://www.linkedin.com/in/anita-forbes-19862bb5/", "Function": "Contractor", "Location": "[\"Florida\"]", "Company": "[\"https://app.notion.com/p/17b90644d524805588ecf7f399f27e9d\"]"}, "icon": "📋", "content": "## Role\n- Contractor at Kiewit. ([LinkedIn](https://www.linkedin.com/in/anita-forbes-19862bb5/) · Apollo CSV export)"}, {"properties": {"Name": "Robby Miller", "LinkedIn": "https://www.linkedin.com/in/robby-miller-839a0a97/", "Function": "electrician", "Location": "[\"Colorado\"]", "Company": "[\"https://app.notion.com/p/17b90644d524805588ecf7f399f27e9d\"]"}, "icon": "🗂️", "content": "## Role\n- electrician at Kiewit. ([LinkedIn](https://www.linkedin.com/in/robby-miller-839a0a97/) · Apollo CSV export)"}, {"properties": {"Name": "Agustin Lopez", "LinkedIn": "https://www.linkedin.com/in/agustin-lopez-59634329b/", "Function": "Pile driving", "Location": "[\"Texas\"]", "Company": "[\"https://app.notion.com/p/17b90644d524805588ecf7f399f27e9d\"]"}, "icon": "📊", "content": "## Role\n- Pile driving at Kiewit. ([LinkedIn](https://www.linkedin.com/in/agustin-lopez-59634329b/) · Apollo CSV export)"}, {"properties": {"Name": "KURT GRINSTEAD", "LinkedIn": "https://www.linkedin.com/in/kurt-grinstead-b0aa02289/", "Function": "Project Manager", "Location": "[\"USA\"]", "Company": "[\"https://app.notion.com/p/17b90644d524805588ecf7f399f27e9d\"]"}, "icon": "🔨", "content": "## Role\n- Project Manager at Kiewit. ([LinkedIn](https://www.linkedin.com/in/kurt-grinstead-b0aa02289/) · Apollo CSV export)"}, {"properties": {"Name": "PATRICK FAY", "LinkedIn": "https://www.linkedin.com/in/patrick-fay-b01b82181/", "Function": "Field Engineer", "Location": "[\"New York City\"]", "Company": "[\"https://app.notion.com/p/17b90644d524805588ecf7f399f27e9d\"]"}, "icon": "⛏️", "content": "## Role\n- Field Engineer at Kiewit. ([LinkedIn](https://www.linkedin.com/in/patrick-fay-b01b82181/) · Apollo CSV export)"}, {"properties": {"Name": "Jake Dornbrack", "LinkedIn": "https://www.linkedin.com/in/jake-dornbrack-2b08a316/", "Function": "Engineer", "Location": "[\"Colorado\"]", "Company": "[\"https://app.notion.com/p/17b90644d524805588ecf7f399f27e9d\"]"}, "icon": "🚧", "content": "## Role\n- Engineer at Kiewit. ([LinkedIn](https://www.linkedin.com/in/jake-dornbrack-2b08a316/) · Apollo CSV export)"}, {"properties": {"Name": "Josh VonMoos", "LinkedIn": "https://www.linkedin.com/in/josh-vonmoos-b084785b/", "Function": "Mechanic", "Location": "[\"Washington\"]", "Company": "[\"https://app.notion.com/p/17b90644d524805588ecf7f399f27e9d\"]"}, "icon": "🏛️", "content": "## Role\n- Mechanic at Kiewit. ([LinkedIn](https://www.linkedin.com/in/josh-vonmoos-b084785b/) · Apollo CSV export)"}, {"properties": {"Name": "Allen Tomlinson", "LinkedIn": "https://www.linkedin.com/in/allen-tomlinson-273209a7/", "Function": "Journeymen electrician", "Location": "[\"Indiana\"]", "Company": "[\"https://app.notion.com/p/17b90644d524805588ecf7f399f27e9d\"]"}, "icon": "🏭", "content": "## Role\n- Journeymen electrician at Kiewit. ([LinkedIn](https://www.linkedin.com/in/allen-tomlinson-273209a7/) · Apollo CSV export)"}, {"properties": {"Name": "Kiki Kouete", "LinkedIn": "https://www.linkedin.com/in/kiki-kouete-753a87168/", "Function": "Senior AP Subcontract compliance and Reporting Analyst", "Location": "[\"USA\"]", "Company": "[\"https://app.notion.com/p/17b90644d524805588ecf7f399f27e9d\"]"}, "icon": "📏", "content": "## Role\n- Senior AP Subcontract compliance and Reporting Analyst at Kiewit. ([LinkedIn](https://www.linkedin.com/in/kiki-kouete-753a87168/) · Apollo CSV export)"}, {"properties": {"Name": "Ryan Naught", "LinkedIn": "https://www.linkedin.com/in/ryan-naught-47b57b40/", "Function": "Superintendent", "Location": "[\"USA\"]", "Company": "[\"https://app.notion.com/p/17b90644d524805588ecf7f399f27e9d\"]"}, "icon": "🔬", "content": "## Role\n- Superintendent at Kiewit. ([LinkedIn](https://www.linkedin.com/in/ryan-naught-47b57b40/) · Apollo CSV export)"}, {"properties": {"Name": "Pablo Torres", "LinkedIn": "https://www.linkedin.com/in/pablo-torres-b491b014a/", "Function": "Manufacturing Engineer", "Location": "[\"Texas\"]", "Company": "[\"https://app.notion.com/p/17b90644d524805588ecf7f399f27e9d\"]"}, "icon": "👷", "content": "## Role\n- Manufacturing Engineer at Kiewit. ([LinkedIn](https://www.linkedin.com/in/pablo-torres-b491b014a/) · Apollo CSV export)"}, {"properties": {"Name": "Brittany Garrison", "LinkedIn": "https://www.linkedin.com/in/brittany-garrison-33982634/", "Function": "Financial Analyst", "Location": "[\"USA\"]", "Company": "[\"https://app.notion.com/p/17b90644d524805588ecf7f399f27e9d\"]"}, "icon": "🏗️", "content": "## Role\n- Financial Analyst at Kiewit. ([LinkedIn](https://www.linkedin.com/in/brittany-garrison-33982634/) · Apollo CSV export)"}, {"properties": {"Name": "Sophie Allgood", "LinkedIn": "https://www.linkedin.com/in/sophie-allgood-2a8039207/", "Function": "Environmental Intern", "Location": "[\"USA\"]", "Company": "[\"https://app.notion.com/p/17b90644d524805588ecf7f399f27e9d\"]"}, "icon": "🧱", "content": "## Role\n- Environmental Intern at Kiewit. ([LinkedIn](https://www.linkedin.com/in/sophie-allgood-2a8039207/) · Apollo CSV export)"}, {"properties": {"Name": "Priyanka Mehta", "LinkedIn": "https://www.linkedin.com/in/priyanka-mehta-136b3315a/", "Function": "Sr. Data Engineer", "Location": "[\"Kansas\"]", "Company": "[\"https://app.notion.com/p/17b90644d524805588ecf7f399f27e9d\"]"}, "icon": "📐", "content": "## Role\n- Sr. Data Engineer at Kiewit. ([LinkedIn](https://www.linkedin.com/in/priyanka-mehta-136b3315a/) · Apollo CSV export)"}, {"properties": {"Name": "Chad Robinson", "LinkedIn": "https://www.linkedin.com/in/chad-robinson-935b9777/", "Function": "Pile driver", "Location": "[\"California\"]", "Company": "[\"https://app.notion.com/p/17b90644d524805588ecf7f399f27e9d\"]"}, "icon": "⚙️", "content": "## Role\n- Pile driver at Kiewit. ([LinkedIn](https://www.linkedin.com/in/chad-robinson-935b9777/) · Apollo CSV export)"}, {"properties": {"Name": "Ronaldo Piedra", "LinkedIn": "https://www.linkedin.com/in/ronaldo-piedra-38a721a3/", "Function": "Structure fitter", "Location": "[\"Texas\"]", "Company": "[\"https://app.notion.com/p/17b90644d524805588ecf7f399f27e9d\"]"}, "icon": "🔧", "content": "## Role\n- Structure fitter at Kiewit. ([LinkedIn](https://www.linkedin.com/in/ronaldo-piedra-38a721a3/) · Apollo CSV export)"}, {"properties": {"Name": "Mark Folk", "LinkedIn": "https://www.linkedin.com/in/mark-folk-1444a55/", "Function": "Gen.Piping Supt.", "Location": "[\"Kansas\"]", "Company": "[\"https://app.notion.com/p/17b90644d524805588ecf7f399f27e9d\"]"}, "icon": "🔩", "content": "## Role\n- Gen.Piping Supt. at Kiewit Industrial Company. ([LinkedIn](https://www.linkedin.com/in/mark-folk-1444a55/) · Apollo CSV export)"}, {"properties": {"Name": "Jason Leonard", "LinkedIn": "https://www.linkedin.com/in/jason-leonard-02b385241/", "Function": "Field Engineer", "Location": "[\"Colorado\"]", "Company": "[\"https://app.notion.com/p/17b90644d524805588ecf7f399f27e9d\"]"}, "icon": "🏢", "content": "## Role\n- Field Engineer at Kiewit. ([LinkedIn](https://www.linkedin.com/in/jason-leonard-02b385241/) · Apollo CSV export)"}, {"properties": {"Name": "Michael Lamb", "LinkedIn": "https://www.linkedin.com/in/michael-lamb-64a46220/", "Function": "Senior Network Technician", "Location": "[\"USA\"]", "Company": "[\"https://app.notion.com/p/17b90644d524805588ecf7f399f27e9d\"]"}, "icon": "📋", "content": "## Role\n- Senior Network Technician at Kiewit. ([LinkedIn](https://www.linkedin.com/in/michael-lamb-64a46220/) · Apollo CSV export)"}, {"properties": {"Name": "Terry Poulsen", "LinkedIn": "https://www.linkedin.com/in/terry-poulsen-9a906740/", "Function": "Maintenance Supervisor", "Location": "[\"Idaho\"]", "Company": "[\"https://app.notion.com/p/17b90644d524805588ecf7f399f27e9d\"]"}, "icon": "🗂️", "content": "## Role\n- Maintenance Supervisor at Kiewit. ([LinkedIn](https://www.linkedin.com/in/terry-poulsen-9a906740/) · Apollo CSV export)"}, {"properties": {"Name": "Gilibaldo Delafuente", "LinkedIn": "https://www.linkedin.com/in/gilibaldo-delafuente-2b3a90127/", "Function": "Structural Welder Foreman", "Location": "[\"Texas\"]", "Company": "[\"https://app.notion.com/p/17b90644d524805588ecf7f399f27e9d\"]"}, "icon": "📊", "content": "## Role\n- Structural Welder Foreman at Kiewit. ([LinkedIn](https://www.linkedin.com/in/gilibaldo-delafuente-2b3a90127/) · Apollo CSV export)"}, {"properties": {"Name": "Kiewit Mike", "LinkedIn": "https://www.linkedin.com/in/kiewit-mike-82b9695a/", "Function": "Project Manager", "Location": "[\"USA\"]", "Company": "[\"https://app.notion.com/p/17b90644d524805588ecf7f399f27e9d\"]"}, "icon": "🔨", "content": "## Role\n- Project Manager at Kiewit Infrastructure West Co.. ([LinkedIn](https://www.linkedin.com/in/kiewit-mike-82b9695a/) · Apollo CSV export)"}, {"properties": {"Name": "Kathy. Allen", "LinkedIn": "https://www.linkedin.com/in/kathy-allen-97009490/", "Function": "Staff Accountant", "Location": "[\"USA\"]", "Company": "[\"https://app.notion.com/p/17b90644d524805588ecf7f399f27e9d\"]"}, "icon": "⛏️", "content": "## Role\n- Staff Accountant at Kiewit. ([LinkedIn](https://www.linkedin.com/in/kathy-allen-97009490/) · Apollo CSV export)"}]